{
  "required": true,
  "package": "com.ddoerr.scriptit.mixin",
  "compatibilityLevel": "JAVA_8",
  "mixins": [
  ],
  "client": [
    "KeyBindingAccessor",
    "PacketTextAccessor",
    "SendPacketTextAccessor",
    "MixinClientPlayerNetworkHandler",
    "MixinScreen",
    "MixinSleepingChatScreen",
    "MessagesAccessor",
    "FpsAccessor",
    "ActiveMouseButtonAccessor",
    "ContainerAccessor",
    "CreativeInventoryAccessor",
    "MixinGameRenderer"
  ],
  "injectors": {
    "defaultRequire": 1
  }
}